[{"id":1,"first_name":"Austine","last_name":"Kiera","email":"akiera0@ezinearticles.com","gender":"Female","salary":722567,"age":97},
{"id":2,"first_name":"Jeremie","last_name":"Buessen","email":"jbuessen1@vinaora.com","gender":"Male","salary":860746,"age":56},
{"id":3,"first_name":"Constantine","last_name":"Antrag","email":"cantrag2@bluehost.com","gender":"Female","salary":390673,"age":13},
{"id":4,"first_name":"Dyan","last_name":"Slark","email":"dslark3@pinterest.com","gender":"Female","salary":934230,"age":21},
{"id":5,"first_name":"Collin","last_name":"Perrycost","email":"cperrycost4@topsy.com","gender":"Male","salary":168070,"age":34},
{"id":6,"first_name":"Phip","last_name":"Harborow","email":"pharborow5@ebay.com","gender":"Male","salary":549864,"age":95},
{"id":7,"first_name":"Teodora","last_name":"Courtliff","email":"tcourtliff6@dyndns.org","gender":"Female","salary":421961,"age":78},
{"id":8,"first_name":"Issiah","last_name":"Mogie","email":"imogie7@printfriendly.com","gender":"Male","salary":290109,"age":90},
{"id":9,"first_name":"Samaria","last_name":"Ioselevich","email":"sioselevich8@samsung.com","gender":"Female","salary":529688,"age":56},
{"id":10,"first_name":"Blanch","last_name":"Guymer","email":"bguymer9@cbsnews.com","gender":"Female","salary":748086,"age":83},
{"id":11,"first_name":"Karon","last_name":"Sleeford","email":"ksleeforda@cbslocal.com","gender":"Female","salary":315206,"age":69},
{"id":12,"first_name":"Dayna","last_name":"Blackden","email":"dblackdenb@vimeo.com","gender":"Female","salary":224458,"age":29},
{"id":13,"first_name":"Keenan","last_name":"Fintoph","email":"kfintophc@usda.gov","gender":"Male","salary":748468,"age":79},
{"id":14,"first_name":"Ashbey","last_name":"Delmonti","email":"adelmontid@ocn.ne.jp","gender":"Agender","salary":281729,"age":20},
{"id":15,"first_name":"Ddene","last_name":"Ferriday","email":"dferridaye@google.de","gender":"Female","salary":26952,"age":50},
{"id":16,"first_name":"Benedick","last_name":"Romme","email":"brommef@netvibes.com","gender":"Male","salary":203012,"age":82},
{"id":17,"first_name":"Chip","last_name":"Bonnett","email":"cbonnettg@utexas.edu","gender":"Male","salary":389081,"age":64},
{"id":18,"first_name":"Arleyne","last_name":"Reek","email":"areekh@cloudflare.com","gender":"Female","salary":129877,"age":95},
{"id":19,"first_name":"Sterne","last_name":"Snowling","email":"ssnowlingi@is.gd","gender":"Male","salary":78820,"age":11},
{"id":20,"first_name":"Phebe","last_name":"Whyffen","email":"pwhyffenj@e-recht24.de","gender":"Female","salary":834553,"age":85},
{"id":21,"first_name":"Jerrome","last_name":"Ballantyne","email":"jballantynek@yelp.com","gender":"Male","salary":977081,"age":70},
{"id":22,"first_name":"Wynnie","last_name":"Cossington","email":"wcossingtonl@bravesites.com","gender":"Female","salary":518617,"age":11},
{"id":23,"first_name":"Dorolice","last_name":"Etherton","email":"dethertonm@pinterest.com","gender":"Female","salary":853689,"age":27},
{"id":24,"first_name":"Helge","last_name":"Kingh","email":"hkinghn@163.com","gender":"Female","salary":15975,"age":91},
{"id":25,"first_name":"Herb","last_name":"Sotham","email":"hsothamo@dailymotion.com","gender":"Male","salary":77491,"age":94},
{"id":26,"first_name":"Otha","last_name":"Fettiplace","email":"ofettiplacep@marketwatch.com","gender":"Female","salary":889979,"age":96},
{"id":27,"first_name":"Drud","last_name":"Esselen","email":"desselenq@ca.gov","gender":"Non-binary","salary":674351,"age":81},
{"id":28,"first_name":"Ronica","last_name":"Vane","email":"rvaner@vkontakte.ru","gender":"Female","salary":342672,"age":81},
{"id":29,"first_name":"Joycelin","last_name":"Pellamont","email":"jpellamonts@ted.com","gender":"Female","salary":666350,"age":94},
{"id":30,"first_name":"Marty","last_name":"Lighterness","email":"mlighternesst@sogou.com","gender":"Female","salary":209540,"age":55},
{"id":31,"first_name":"Price","last_name":"Gutsell","email":"pgutsellu@newsvine.com","gender":"Male","salary":154691,"age":80},
{"id":32,"first_name":"Elisa","last_name":"Sproat","email":"esproatv@pbs.org","gender":"Female","salary":451113,"age":35},
{"id":33,"first_name":"Kristen","last_name":"Lippini","email":"klippiniw@e-recht24.de","gender":"Female","salary":366826,"age":16},
{"id":34,"first_name":"Wenda","last_name":"Fortey","email":"wforteyx@surveymonkey.com","gender":"Female","salary":877747,"age":95},
{"id":35,"first_name":"Garrot","last_name":"Rickhuss","email":"grickhussy@over-blog.com","gender":"Male","salary":829394,"age":38},
{"id":36,"first_name":"Meredith","last_name":"Pady","email":"mpadyz@themeforest.net","gender":"Female","salary":377655,"age":94},
{"id":37,"first_name":"Patty","last_name":"Lack","email":"plack10@ycombinator.com","gender":"Male","salary":268826,"age":66},
{"id":38,"first_name":"Tracie","last_name":"Powney","email":"tpowney11@npr.org","gender":"Female","salary":241055,"age":62},
{"id":39,"first_name":"Dennison","last_name":"Hayen","email":"dhayen12@gmpg.org","gender":"Male","salary":359076,"age":37},
{"id":40,"first_name":"Wyatan","last_name":"Roseblade","email":"wroseblade13@delicious.com","gender":"Male","salary":579632,"age":60},
{"id":41,"first_name":"Zitella","last_name":"Spencley","email":"zspencley14@pinterest.com","gender":"Female","salary":16040,"age":95},
{"id":42,"first_name":"Menard","last_name":"O'Regan","email":"moregan15@umn.edu","gender":"Male","salary":39254,"age":55},
{"id":43,"first_name":"Scarface","last_name":"Marchello","email":"smarchello16@liveinternet.ru","gender":"Male","salary":647651,"age":92},
{"id":44,"first_name":"Eddi","last_name":"Canet","email":"ecanet17@amazon.de","gender":"Female","salary":858244,"age":19},
{"id":45,"first_name":"Vere","last_name":"Bradborne","email":"vbradborne18@godaddy.com","gender":"Female","salary":337363,"age":89},
{"id":46,"first_name":"Lawton","last_name":"Tinline","email":"ltinline19@sina.com.cn","gender":"Male","salary":155257,"age":83},
{"id":47,"first_name":"Freda","last_name":"Gerrard","email":"fgerrard1a@bluehost.com","gender":"Female","salary":392960,"age":51},
{"id":48,"first_name":"Garret","last_name":"Larrington","email":"glarrington1b@acquirethisname.com","gender":"Male","salary":761324,"age":79},
{"id":49,"first_name":"Dalia","last_name":"Bowcock","email":"dbowcock1c@hao123.com","gender":"Female","salary":395456,"age":38},
{"id":50,"first_name":"Gideon","last_name":"Alejo","email":"galejo1d@tinyurl.com","gender":"Female","salary":374059,"age":89},
{"id":51,"first_name":"Thea","last_name":"Southcombe","email":"tsouthcombe1e@marriott.com","gender":"Female","salary":618092,"age":31},
{"id":52,"first_name":"Ezra","last_name":"Najera","email":"enajera1f@europa.eu","gender":"Male","salary":921385,"age":39},
{"id":53,"first_name":"Salome","last_name":"Broadbear","email":"sbroadbear1g@unesco.org","gender":"Female","salary":330504,"age":26},
{"id":54,"first_name":"Quincey","last_name":"Dwire","email":"qdwire1h@state.gov","gender":"Male","salary":740993,"age":22},
{"id":55,"first_name":"Paula","last_name":"Tidmas","email":"ptidmas1i@bloglines.com","gender":"Female","salary":969745,"age":27},
{"id":56,"first_name":"Christyna","last_name":"Roumier","email":"croumier1j@mac.com","gender":"Female","salary":24272,"age":45},
{"id":57,"first_name":"Skyler","last_name":"Shenton","email":"sshenton1k@homestead.com","gender":"Male","salary":382368,"age":97},
{"id":58,"first_name":"Glyn","last_name":"Scollick","email":"gscollick1l@flickr.com","gender":"Male","salary":762196,"age":28},
{"id":59,"first_name":"Murray","last_name":"Engall","email":"mengall1m@wikipedia.org","gender":"Male","salary":581316,"age":36},
{"id":60,"first_name":"Pyotr","last_name":"McCreath","email":"pmccreath1n@drupal.org","gender":"Male","salary":561982,"age":82},
{"id":61,"first_name":"Reiko","last_name":"Barhem","email":"rbarhem1o@yandex.ru","gender":"Female","salary":911449,"age":14},
{"id":62,"first_name":"Yancey","last_name":"Overal","email":"yoveral1p@indiegogo.com","gender":"Male","salary":883477,"age":58},
{"id":63,"first_name":"Blithe","last_name":"Kilford","email":"bkilford1q@ihg.com","gender":"Female","salary":621108,"age":90},
{"id":64,"first_name":"Bartel","last_name":"Van der Daal","email":"bvanderdaal1r@scribd.com","gender":"Male","salary":190134,"age":91},
{"id":65,"first_name":"Vally","last_name":"Peasee","email":"vpeasee1s@com.com","gender":"Female","salary":631464,"age":32},
{"id":66,"first_name":"Bink","last_name":"Bernucci","email":"bbernucci1t@nih.gov","gender":"Genderfluid","salary":412334,"age":31},
{"id":67,"first_name":"Garv","last_name":"Yerill","email":"gyerill1u@ifeng.com","gender":"Male","salary":894909,"age":99},
{"id":68,"first_name":"Lindsey","last_name":"Garlant","email":"lgarlant1v@macromedia.com","gender":"Female","salary":529578,"age":38},
{"id":69,"first_name":"Vanessa","last_name":"Jotcham","email":"vjotcham1w@usda.gov","gender":"Female","salary":258630,"age":93},
{"id":70,"first_name":"Honoria","last_name":"Jordison","email":"hjordison1x@nydailynews.com","gender":"Female","salary":897074,"age":55},
{"id":71,"first_name":"Renaud","last_name":"Hulbert","email":"rhulbert1y@tamu.edu","gender":"Male","salary":870639,"age":31},
{"id":72,"first_name":"Uta","last_name":"Rosencrantz","email":"urosencrantz1z@ameblo.jp","gender":"Polygender","salary":119682,"age":99},
{"id":73,"first_name":"Celle","last_name":"McClements","email":"cmcclements20@printfriendly.com","gender":"Female","salary":668833,"age":71},
{"id":74,"first_name":"Laina","last_name":"Fishpoole","email":"lfishpoole21@bloglines.com","gender":"Female","salary":354345,"age":98},
{"id":75,"first_name":"Baudoin","last_name":"Hatherleigh","email":"bhatherleigh22@samsung.com","gender":"Male","salary":871425,"age":80},
{"id":76,"first_name":"Robby","last_name":"Passman","email":"rpassman23@wikia.com","gender":"Male","salary":230867,"age":94},
{"id":77,"first_name":"Giana","last_name":"Furlonge","email":"gfurlonge24@java.com","gender":"Female","salary":311223,"age":64},
{"id":78,"first_name":"Adolf","last_name":"Summerfield","email":"asummerfield25@deviantart.com","gender":"Male","salary":305826,"age":56},
{"id":79,"first_name":"Justinian","last_name":"Hannah","email":"jhannah26@omniture.com","gender":"Male","salary":151776,"age":56},
{"id":80,"first_name":"Pearla","last_name":"McGerr","email":"pmcgerr27@aboutads.info","gender":"Polygender","salary":191035,"age":54},
{"id":81,"first_name":"Thebault","last_name":"Dallender","email":"tdallender28@webnode.com","gender":"Male","salary":898478,"age":31},
{"id":82,"first_name":"Riley","last_name":"Niles","email":"rniles29@kickstarter.com","gender":"Male","salary":613717,"age":55},
{"id":83,"first_name":"Briney","last_name":"Janse","email":"bjanse2a@paypal.com","gender":"Female","salary":949302,"age":64},
{"id":84,"first_name":"Sibelle","last_name":"Brunesco","email":"sbrunesco2b@cisco.com","gender":"Female","salary":978073,"age":86},
{"id":85,"first_name":"Adriano","last_name":"Ditzel","email":"aditzel2c@opera.com","gender":"Male","salary":399625,"age":58},
{"id":86,"first_name":"Garfield","last_name":"MacSherry","email":"gmacsherry2d@etsy.com","gender":"Male","salary":879500,"age":41},
{"id":87,"first_name":"Honor","last_name":"Cobain","email":"hcobain2e@usgs.gov","gender":"Female","salary":402164,"age":74},
{"id":88,"first_name":"Friedrick","last_name":"MacAless","email":"fmacaless2f@huffingtonpost.com","gender":"Male","salary":903974,"age":35},
{"id":89,"first_name":"Sophey","last_name":"Beceril","email":"sbeceril2g@seesaa.net","gender":"Female","salary":269375,"age":32},
{"id":90,"first_name":"Olympie","last_name":"Ledekker","email":"oledekker2h@sakura.ne.jp","gender":"Female","salary":168527,"age":36},
{"id":91,"first_name":"Jasun","last_name":"Lammiman","email":"jlammiman2i@skyrock.com","gender":"Agender","salary":880346,"age":10},
{"id":92,"first_name":"Herve","last_name":"Hammond","email":"hhammond2j@weather.com","gender":"Male","salary":267814,"age":69},
{"id":93,"first_name":"Gilly","last_name":"Eggers","email":"geggers2k@google.fr","gender":"Genderfluid","salary":146607,"age":82},
{"id":94,"first_name":"Ingra","last_name":"Haddington","email":"ihaddington2l@lycos.com","gender":"Male","salary":564943,"age":12},
{"id":95,"first_name":"Elvis","last_name":"Pamment","email":"epamment2m@over-blog.com","gender":"Male","salary":401625,"age":46},
{"id":96,"first_name":"Beatrix","last_name":"O'Towey","email":"botowey2n@odnoklassniki.ru","gender":"Female","salary":171176,"age":13},
{"id":97,"first_name":"Angel","last_name":"Wales","email":"awales2o@ovh.net","gender":"Female","salary":895507,"age":95},
{"id":98,"first_name":"Danni","last_name":"Matteotti","email":"dmatteotti2p@amazon.de","gender":"Agender","salary":997335,"age":57},
{"id":99,"first_name":"Flossie","last_name":"Dedham","email":"fdedham2q@microsoft.com","gender":"Female","salary":15260,"age":88},
{"id":100,"first_name":"Tucker","last_name":"Jennrich","email":"tjennrich2r@addthis.com","gender":"Male","salary":906342,"age":50}]